LICENSE.txt
MANIFEST.in
README.rst
VERSION.py
setup.cfg
setup.py
certif_pyspec.egg-info/PKG-INFO
certif_pyspec.egg-info/SOURCES.txt
certif_pyspec.egg-info/dependency_links.txt
certif_pyspec.egg-info/requires.txt
certif_pyspec.egg-info/top_level.txt
pyspec/VERSION.py
pyspec/__init__.py
pyspec/css_logger.py
pyspec/ordereddict.py
pyspec/utils.py
pyspec/client/SpecArray.py
pyspec/client/SpecChannel.py
pyspec/client/SpecClientError.py
pyspec/client/SpecCommand.py
pyspec/client/SpecConnection.py
pyspec/client/SpecConnectionsManager.py
pyspec/client/SpecCounter.py
pyspec/client/SpecEventsDispatcher.py
pyspec/client/SpecMessage.py
pyspec/client/SpecMotor.py
pyspec/client/SpecReply.py
pyspec/client/SpecScan.py
pyspec/client/SpecServer.py
pyspec/client/SpecVariable.py
pyspec/client/SpecWaitObject.py
pyspec/client/__init__.py
pyspec/client/saferef.py
pyspec/client/spec_shm.py
pyspec/client/spec_updater.py
pyspec/client/test_conn.py
pyspec/client/testpy.py
pyspec/client/tests.py
pyspec/client/wait_object.py
pyspec/datashm/datashm_py.c
pyspec/datashm/spec_shm.h
pyspec/datashm/sps.c
pyspec/datashm/sps.h
pyspec/doc/SpecHTMLreST.py
pyspec/doc/SpecMANreST.py
pyspec/doc/__init__.py
pyspec/file/__init__.py
pyspec/file/h5datasets.py
pyspec/file/hamamatsu.py
pyspec/file/hdf5.py
pyspec/file/spec.py
pyspec/file/testspec.py
pyspec/file/tiff.py
pyspec/graphics/PyQt4_import.py
pyspec/graphics/PyQt5_import.py
pyspec/graphics/PyQt6_import.py
pyspec/graphics/PySide2_import.py
pyspec/graphics/PySide6_import.py
pyspec/graphics/PySide_import.py
pyspec/graphics/QVariant.py
pyspec/graphics/__init__.py
pyspec/graphics/graphics_rc.py
pyspec/graphics/matplotlib_import.py
pyspec/graphics/qwt_import.py
pyspec/hardware/__init__.py
pyspec/hardware/server.py
pyspec/tools/__init__.py
pyspec/tools/roi_selector.py
pyspec/tools/specfile.py
python/VERSION.py
python/__init__.py
python/css_logger.py
python/ordereddict.py
python/utils.py
python/client/SpecArray.py
python/client/SpecChannel.py
python/client/SpecClientError.py
python/client/SpecCommand.py
python/client/SpecConnection.py
python/client/SpecConnectionsManager.py
python/client/SpecCounter.py
python/client/SpecEventsDispatcher.py
