Metadata-Version: 1.1
Name: certif-pyspec
Version: 1.5.3
Summary: Python SPEC modules and tools
Home-page: http://github.com/txolutions/pyspec
Author: TXOlutions
Author-email: txo@txolutions.com
License: UNKNOWN
Download-URL: https://pypi.org/projects/certif-pyspec/
Platform: UNKNOWN
